nh3-0.3.0.dist-info/METADATA
nh3-0.3.0.dist-info/WHEEL
nh3-0.3.0.dist-info/licenses/LICENSE
nh3.libs/libgcc_s-5b5488a6.so.1
nh3/__init__.py
nh3/__init__.pyi
nh3/nh3.cpython-313t-arm-linux-musleabihf.so
nh3/py.typed
nh3-0.3.0.dist-info/RECORD
