Metadata-Version: 2.4
Name: nh3
Version: 0.3.0
Classifier: Programming Language :: Rust
Classifier: Programming Language :: Python :: Implementation :: CPython
Classifier: Programming Language :: Python :: Implementation :: PyPy
Classifier: Topic :: Software Development :: Libraries :: Python Modules
License-File: LICENSE
Summary: Python binding to Ammonia HTML sanitizer Rust crate
Author: messense <messense@icloud.com>
Author-email: messense <messense@icloud.com>
License: MIT
Requires-Python: >=3.8
Project-URL: Source Code, https://github.com/messense/nh3
